AUTHORS
LICENSE
MANIFEST.in
NEWS.rst
README.rst
setup.cfg
setup.py
tox.ini
doc/Makefile
doc/bugs.rst
doc/conf.py
doc/contributing.rst
doc/index.rst
doc/install.rst
doc/license.rst
doc/problems.rst
doc/quickstart.rst
doc/release.rst
doc/wild.rst
doc/.templates/layout.html
doc/api/client.rst
doc/api/commit.rst
doc/api/core.rst
doc/api/index.rst
doc/api/issues.rst
doc/api/network.rst
doc/api/object.rst
doc/api/organizations.rst
doc/api/pull_requests.rst
doc/api/repos.rst
doc/api/request.rst
doc/api/teams.rst
doc/api/users.rst
examples/friend-or-follow.py
github2/DigiCert_High_Assurance_EV_Root_CA.crt
github2/__init__.py
github2/_version.py
github2/client.py
github2/commits.py
github2/core.py
github2/issues.py
github2/organizations.py
github2/pull_requests.py
github2/repositories.py
github2/request.py
github2/teams.py
github2/users.py
github2.egg-info/PKG-INFO
github2.egg-info/SOURCES.txt
github2.egg-info/dependency_links.txt
github2.egg-info/entry_points.txt
github2.egg-info/requires.txt
github2.egg-info/top_level.txt
github2.egg-info/zip-safe
github2/bin/__init__.py
github2/bin/manage_collaborators.py
github2/bin/search_repos.py
tests/test_charset_header.py
tests/test_commits.py
tests/test_date_handling.py
tests/test_issues.py
tests/test_organizations.py
tests/test_pull_requests.py
tests/test_regression.py
tests/test_repositories.py
tests/test_request.py
tests/test_teams.py
tests/test_tz_aware_date_handling.py
tests/test_unit.py
tests/test_user.py
tests/utils.py
tests/data/github.com,api,v2,json,commits,list,JNRowe,jnrowe-misc,master,a252487bd992cdfc8247b3c41d0cb9fa
tests/data/github.com,api,v2,json,commits,list,JNRowe,misc-overlay,gh-pages,d0ce7ae70e44f7f396a93485a24b3423
tests/data/github.com,api,v2,json,commits,list,JNRowe,misc-overlay,gh-pages,packages,dev-python.html,8622bc5e052f03439528cc9b7bf3fea2
tests/data/github.com,api,v2,json,commits,list,JNRowe,misc-overlay,master,Makefile,75d9a1e41e76c3b924420d48b56dc756
tests/data/github.com,api,v2,json,commits,list,JNRowe,misc-overlay,master,bfb4f990e48c87dab73d988a81318d69
tests/data/github.com,api,v2,json,commits,show,ask,python-github2,1c83cde9b5a7c396a01af1007fb7b88765b9ae45,a4f58221c8131c4e0975cd806f13d76c
