Metadata-Version: 1.0
Name: github2
Version: 0.6.1
Summary: Github API v2 library for Python
Home-page: http://github.com/ask/python-github2
Author: Ask Solem
Author-email: askh@opera.com
License: BSD
Keywords: git github api
Platform: any
Classifier: Development Status :: 5 - Production/Stable
Classifier: Intended Audience :: Developers
Classifier: License :: OSI Approved :: BSD License
Classifier: Operating System :: OS Independent
Classifier: Programming Language :: Python
Classifier: Programming Language :: Python :: 2
Classifier: Programming Language :: Python :: 2.4
Classifier: Programming Language :: Python :: 2.5
Classifier: Programming Language :: Python :: 2.6
Classifier: Programming Language :: Python :: 2.7
Classifier: Programming Language :: Python :: 3
Classifier: Programming Language :: Python :: 3.1
Classifier: Programming Language :: Python :: 3.2
Classifier: Topic :: Software Development
Classifier: Topic :: Software Development :: Libraries
